Metadata-Version: 1.1
Name: jsmin
Version: 2.0.8
Summary: JavaScript minifier.
Home-page: https://bitbucket.org/dcs/jsmin/
Author: Tikitu de Jager
Author-email: tikitu+jsmin@logophile.org
License: MIT License
Platform: UNKNOWN
Classifier: Development Status :: 5 - Production/Stable
Classifier: Environment :: Web Environment
Classifier: Intended Audience :: Developers
Classifier: License :: OSI Approved :: MIT License
Classifier: Operating System :: OS Independent
Classifier: Programming Language :: Python :: 2
Classifier: Programming Language :: Python :: 2.6
Classifier: Programming Language :: Python :: 2.7
Classifier: Programming Language :: Python :: 3
Classifier: Programming Language :: Python :: 3.2
Classifier: Programming Language :: Python :: 3.3
Classifier: Topic :: Internet :: WWW/HTTP :: Dynamic Content
Classifier: Topic :: Software Development :: Pre-processors
Classifier: Topic :: Text Processing :: Filters
